coned/__init__.py
coned/meter.py
oru/__init__.py
oru/meter.py
coned-0.4.0.dist-info/LICENSE
coned-0.4.0.dist-info/METADATA
coned-0.4.0.dist-info/WHEEL
coned-0.4.0.dist-info/entry_points.txt
coned-0.4.0.dist-info/top_level.txt
coned-0.4.0.dist-info/RECORD
