Metadata-Version: 2.1
Name: coned
Version: 0.4.0
Summary: Python client for ConEdison smart energy meters
Home-page: https://github.com/bvlaicu/coned/
Author: Bogdan Vlaicu
Author-email: bogdanvlaicu@yahoo.com
License: Apache Software License
Platform: any
Classifier: Programming Language :: Python
Classifier: Programming Language :: Python :: 2
Classifier: Programming Language :: Python :: 3
Classifier: Development Status :: 4 - Beta
Classifier: Natural Language :: English
Classifier: Environment :: Web Environment
Classifier: Intended Audience :: Developers
Classifier: License :: OSI Approved :: Apache Software License
Classifier: Operating System :: OS Independent
Classifier: Topic :: Software Development :: Libraries :: Python Modules
Classifier: Topic :: Software Development :: Libraries :: Application Frameworks
Classifier: Topic :: Internet :: WWW/HTTP :: Dynamic Content
License-File: LICENSE
Requires-Dist: requests
Requires-Dist: pyppeteer
Requires-Dist: pyotp
Provides-Extra: testing
Requires-Dist: pytest ; extra == 'testing'
